CPT_GFFParser/CPT_GFFParser.py
CPT_GFFParser/CPT_ParserHelpers.py
CPT_GFFParser/__init__.py
CPT_GFFParser/gffSeqFeature.py
CPT_GFFParser/setup.py
CPT_GFFParser-1.2.2.dist-info/LICENSE
CPT_GFFParser-1.2.2.dist-info/METADATA
CPT_GFFParser-1.2.2.dist-info/WHEEL
CPT_GFFParser-1.2.2.dist-info/top_level.txt
CPT_GFFParser-1.2.2.dist-info/RECORD
