Metadata-Version: 2.1
Name: CPT-GFFParser
Version: 1.2.2
Summary: A Biopython extension package for I/O of GFF files
Home-page: https://pypi.org/project/CPT-GFFParser/
Author: Anthony Criscione
Author-email: talkingbeaverthing@gmail.com
License: LICENSE.txt
Project-URL: Bug Tracker, https://github.com/TAMU-CPT/CPT_GffParser/issues
Keywords: gff gff3 bioinformatics python biopython
Platform: UNKNOWN
Classifier: Programming Language :: Python :: 3
Classifier: License :: OSI Approved :: BSD License
Classifier: Operating System :: OS Independent
Requires-Python: >=3.7
License-File: LICENSE
Requires-Dist: biopython (>=1.79)
